LICENSE.txt
MANIFEST.in
README.rst
THANKS
build_ffi.py
setup.py
tox.ini
docs/Makefile
docs/changelog.rst
docs/conf.py
docs/index.rst
docs/make.bat
docs/_static/customizations.css
farbox_misaka.egg-info/PKG-INFO
farbox_misaka.egg-info/SOURCES.txt
farbox_misaka.egg-info/dependency_links.txt
farbox_misaka.egg-info/requires.txt
farbox_misaka.egg-info/top_level.txt
misaka/__init__.py
misaka/__init__.pyc
misaka/api.py
misaka/api.pyc
misaka/callbacks.py
misaka/constants.py
misaka/extra.c
misaka/extra.h
misaka/utils.py
misaka/hoedown/autolink.c
misaka/hoedown/autolink.h
misaka/hoedown/buffer.c
misaka/hoedown/buffer.h
misaka/hoedown/document.c
misaka/hoedown/document.h
misaka/hoedown/escape.c
misaka/hoedown/escape.h
misaka/hoedown/html.c
misaka/hoedown/html.h
misaka/hoedown/html_blocks.c
misaka/hoedown/html_smartypants.c
misaka/hoedown/stack.c
misaka/hoedown/stack.h
misaka/hoedown/version.c
misaka/hoedown/version.h
scripts/misaka
tests/__init__.py
tests/chibitest.py
tests/run_tests.py
tests/test_benchmark.py
tests/test_markdown.py
tests/test_misc.py
tests/test_renderer.py
tests/test_smartypants.py
tests/test_xss_protection.py
tests/utils.py
tests/MarkdownTest_1.0/Amps and angle encoding.html
tests/MarkdownTest_1.0/Amps and angle encoding.text
tests/MarkdownTest_1.0/Auto links.html
tests/MarkdownTest_1.0/Auto links.text
tests/MarkdownTest_1.0/Backslash escapes.html
tests/MarkdownTest_1.0/Backslash escapes.text
tests/MarkdownTest_1.0/Blockquotes with code blocks.html
tests/MarkdownTest_1.0/Blockquotes with code blocks.text
tests/MarkdownTest_1.0/Hard-wrapped paragraphs with list-like lines.html
tests/MarkdownTest_1.0/Hard-wrapped paragraphs with list-like lines.text
tests/MarkdownTest_1.0/Horizontal rules.html
tests/MarkdownTest_1.0/Horizontal rules.text
tests/MarkdownTest_1.0/Inline HTML (Advanced).html
tests/MarkdownTest_1.0/Inline HTML (Advanced).text
tests/MarkdownTest_1.0/Inline HTML (Simple).html
tests/MarkdownTest_1.0/Inline HTML (Simple).text
tests/MarkdownTest_1.0/Inline HTML comments.html
tests/MarkdownTest_1.0/Inline HTML comments.text
tests/MarkdownTest_1.0/Links, inline style.html
tests/MarkdownTest_1.0/Links, inline style.text
